[
  {
    "title": "Oshtekk warriors",
    "image": "oshtekk_warriors",
    "twitch": "",
    "youtube": "",
    "twitter": "https://twitter.com/OshTekkWarriors",
    "facebook": "https://www.facebook.com/OshTekkWarriors",
    "instagram": "https://www.instagram.com/oshtekkwarriors"
  },
  {
    "title": "Sudor esports",
    "image": "sudor_esports",
    "twitch": "",
    "youtube": "https://www.youtube.com/c/SudoreSports",
    "twitter": "https://twitter.com/sudoresports",
    "facebook": "",
    "instagram": "https://www.instagram.com/sudoresports"
  },
  {
    "title": "Power eSports",
    "image": "power_esports",
    "twitch": "",
    "youtube": "https://www.youtube.com/user/CLAnPOWR",
    "twitter": "https://twitter.com/POWReSports",
    "facebook": "",
    "instagram": "https://www.instagram.com/poweresports"
  },
  {
    "title": "01 esports",
    "image": "esports_01",
    "twitch": "",
    "youtube": "",
    "twitter": "https://twitter.com/01_esports",
    "facebook": "",
    "instagram": ""
  },
  {
    "title": "Redemption GG",
    "image": "redemption_gg",
    "twitch": "",
    "youtube": "",
    "twitter": "https://twitter.com/RedemGG",
    "facebook": "",
    "instagram": "https://www.instagram.com/redemgg"
  },
  {
    "title": "TUWAIQ",
    "image": "tuwaiq",
    "twitch": "",
    "youtube": "",
    "twitter": "https://twitter.com/TuwaiqClub",
    "facebook": "https://www.facebook.com/Tuwaiqclub",
    "instagram": "https://www.instagram.com/tuwaiqclub"
  },
  {
    "title": "25 eSports",
    "image": "esports_25",
    "twitch": "",
    "youtube": "",
    "twitter": "https://twitter.com/25esports",
    "facebook": "",
    "instagram": "https://www.instagram.com/25esports"
  },
  {
    "title": "Team ultimates",
    "image": "team_ultimates",
    "twitch": "https://www.twitch.tv/theultimatesgg",
    "youtube": "",
    "twitter": "https://twitter.com/theultimatesgg",
    "facebook": "",
    "instagram": "https://www.instagram.com/theultimatesgg"
  },
  {
    "title": "ASMR eSports",
    "image": "tuwaiq",
    "twitch": "",
    "youtube": "https://www.youtube.com/channel/UCmtLzggnPK3Ia-Vf9GW8TvA",
    "twitter": "https://twitter.com/asmresports",
    "facebook": "",
    "instagram": "https://www.instagram.com/asmrclan"
  },
  {
    "title": "FROZ eSports",
    "image": "froz_esports",
    "twitch": "",
    "youtube": "",
    "twitter": "",
    "facebook": "",
    "instagram": "https://www.instagram.com/froz.esports"
  }
]